gitglasses/__init__.py
gitglasses/cli.py
gitglasses/gitglasses.py
gitglasses-0.2.0.dist-info/METADATA
gitglasses-0.2.0.dist-info/WHEEL
gitglasses-0.2.0.dist-info/entry_points.txt
gitglasses-0.2.0.dist-info/licenses/LICENSE
gitglasses-0.2.0.dist-info/RECORD
