Metadata-Version: 2.4
Name: gitglasses
Version: 0.2.0
Summary: Visualize git branch relationships in a commit range
Author: Sander Teunissen
License: MIT
License-File: LICENSE
Requires-Python: >=3.9
Requires-Dist: pygit2>=1.13.0
